quark_twisted_runtime.py
datawire_quarkdev_twisted-0.4.2.dist-info/DESCRIPTION.rst
datawire_quarkdev_twisted-0.4.2.dist-info/METADATA
datawire_quarkdev_twisted-0.4.2.dist-info/RECORD
datawire_quarkdev_twisted-0.4.2.dist-info/WHEEL
datawire_quarkdev_twisted-0.4.2.dist-info/metadata.json
datawire_quarkdev_twisted-0.4.2.dist-info/top_level.txt
