Metadata-Version: 2.0
Name: datawire-quarkdev-twisted
Version: 0.4.2
Summary: Twisted integration for Python code generated by Quark
Home-page: http://datawire.github.io/quark
Author: datawire.io
Author-email: hello@datawire.io
License: Apache License, Version 2.0
Platform: UNKNOWN
Requires-Dist: autobahn[twisted] (==0.10.9)
Requires-Dist: service-identity (==14.0.0)
Requires-Dist: txaio (==1.1)
